Metadata-Version: 2.0
Name: xentica
Version: 0.2.0
Summary: GPU-accelerated engine for multi-dimensional cellular automata
Home-page: https://github.com/a5kin/xentica
Author: Andrey Zamaraev
Author-email: a5kin@github.com
License: MIT
Keywords: cellular automata ca simulation artificial life alife energy framework gpu multidimensional microprograms conservation
Platform: UNKNOWN
Classifier: Development Status :: 3 - Alpha
Classifier: Environment :: Console
Classifier: Intended Audience :: Developers
Classifier: Intended Audience :: Science/Research
Classifier: Topic :: Games/Entertainment :: Simulation
Classifier: Topic :: Scientific/Engineering :: Artificial Life
Classifier: Topic :: Scientific/Engineering :: Physics
Classifier: Topic :: Scientific/Engineering :: Visualization
Classifier: Topic :: Software Development :: Code Generators
Classifier: Topic :: Software Development :: Libraries
Classifier: Topic :: Artistic Software
Classifier: License :: OSI Approved :: MIT License
Classifier: Programming Language :: Python :: 3.5
Classifier: Programming Language :: Python :: 3.6
Classifier: Programming Language :: Python :: 3.7
Classifier: Programming Language :: Python :: 3 :: Only
Classifier: Programming Language :: Python :: Implementation :: CPython
Provides-Extra: test
Provides-Extra: dev
Requires-Dist: numpy
Requires-Dist: cached-property
Provides-Extra: dev
Requires-Dist: check-manifest; extra == 'dev'
Provides-Extra: test
Requires-Dist: coverage; extra == 'test'
